atoml/__init__.py
atoml/_compat.py
atoml/_utils.py
atoml/api.py
atoml/container.py
atoml/exceptions.py
atoml/items.py
atoml/parser.py
atoml/py.typed
atoml/source.py
atoml/toml_char.py
atoml/toml_document.py
atoml/toml_file.py
atoml-1.1.1.dist-info/WHEEL
atoml-1.1.1.dist-info/METADATA
atoml-1.1.1.dist-info/LICENSE
atoml-1.1.1.dist-info/RECORD
